{
  "Tagline": "About Us",
  "Header": "Exceptional Customer Service and Satisfaction Guaranteed",
  "Body": "Power Pressure Wash has been providing top-notch pressure washing services for over 14 years. With a strong commitment to customer service and satisfaction, the owner is present on every job to ensure the highest quality of work. They offer a wide range of services including pressure washing, soft washing, roof cleaning, gutter cleaning, commercial cleaning, and parking lot striping. They operate primarily in Southwest Houston and serve a wide range of cities including Missouri City, Sugarland, Stafford, Fresno, Arcola, Pearland, Pasadena, Rosharon, Katy, Richmond, Rosenberg, Houston, Humble, Cypress, TX. Despite not having any awards, they are recognized by the Better Business Bureau, reflecting their dedication to professional and ethical business practices.",
  "ImageUrl": "https://storage.googleapis.com/image-service-images/5236205469827072/d29a_a_man_using_a_hose_to_clean_a_sidewalk.webp",
  "AltText": "Power Pressure Wash team providing service in Missouri City, TX"
}