{
  "Header": "Experience a clean and fresh property with our expert pressure washing in Southwest Houston.",
  "Body": "Tired of the dirt and grime on your property's exterior? Let Power Pressure Wash help! Our comprehensive services, including pressure washing, roof cleaning, and gutter cleaning, will rejuvenate your property, making it look as good as new.",
  "CTA": "Book today!",
  "ImageUrl": "https://storage.googleapis.com/image-service-images/5236205469827072/d29a_a_man_using_a_hose_to_clean_a_sidewalk.webp",
  "AltText": "Professional pressure washing, roof cleaning, and gutter cleaning in Southwest Houston by Power Pressure Wash.",
  "Anchor": "top"
}